jaqalpaq/__init__.py
jaqalpaq/_cli.py
jaqalpaq/error.py
jaqalpaq/run.py
jaqalpaq/utilities.py
jaqalpaq/core/__init__.py
jaqalpaq/core/block.py
jaqalpaq/core/branch.py
jaqalpaq/core/circuit.py
jaqalpaq/core/circuitbuilder.py
jaqalpaq/core/constant.py
jaqalpaq/core/gate.py
jaqalpaq/core/gatedef.py
jaqalpaq/core/identifier.py
jaqalpaq/core/macro.py
jaqalpaq/core/parameter.py
jaqalpaq/core/register.py
jaqalpaq/core/result.py
jaqalpaq/core/stretch.py
jaqalpaq/core/usepulses.py
jaqalpaq/core/algorithm/__init__.py
jaqalpaq/core/algorithm/expand_macros.py
jaqalpaq/core/algorithm/fill_in_let.py
jaqalpaq/core/algorithm/fill_in_map.py
jaqalpaq/core/algorithm/unit_timing.py
jaqalpaq/core/algorithm/used_qubit_visitor.py
jaqalpaq/core/algorithm/visitor.py
jaqalpaq/core/algorithm/walkers.py
jaqalpaq/emulator/__init__.py
jaqalpaq/emulator/_validator.py
jaqalpaq/emulator/backend.py
jaqalpaq/emulator/frontend.py
jaqalpaq/emulator/pygsti/__init__.py
jaqalpaq/emulator/pygsti/backends.py
jaqalpaq/emulator/pygsti/circuit.py
jaqalpaq/emulator/pygsti/model.py
jaqalpaq/generator/__init__.py
jaqalpaq/generator/generator.py
jaqalpaq/ipc/__init__.py
jaqalpaq/ipc/ipc.py
jaqalpaq/parser/__init__.py
jaqalpaq/parser/identifier.py
jaqalpaq/parser/parser.py
jaqalpaq/parser/slyparse.py
test_JaqalPaq-0.0.1.1.0.0rc2.data/data/share/jaqalpaq/examples/usage_example.py
test_JaqalPaq-0.0.1.1.0.0rc2.data/data/share/jaqalpaq/examples/h2 (molecular hydrogen)/JaqalPaq_H2_Exemplar.ipynb
test_JaqalPaq-0.0.1.1.0.0rc2.data/data/share/jaqalpaq/examples/h2 (molecular hydrogen)/Jaqal_H2_Stretched.ipynb
test_JaqalPaq-0.0.1.1.0.0rc2.data/data/share/jaqalpaq/examples/heh+ (helium hydride)/JaqalPaq_HeH+_Tapered_Exemplar.ipynb
test_JaqalPaq-0.0.1.1.0.0rc2.data/data/share/jaqalpaq/examples/heh+ (helium hydride)/JaqalPaq_HeH+_Untapered_Exemplar.ipynb
test_JaqalPaq-0.0.1.1.0.0rc2.data/data/share/jaqalpaq/examples/jaqal/Sxx_circuit.jaqal
test_JaqalPaq-0.0.1.1.0.0rc2.data/data/share/jaqalpaq/examples/jaqal/bell_prep.jaqal
test_JaqalPaq-0.0.1.1.0.0rc2.dist-info/LICENSE
test_JaqalPaq-0.0.1.1.0.0rc2.dist-info/METADATA
test_JaqalPaq-0.0.1.1.0.0rc2.dist-info/NOTICE
test_JaqalPaq-0.0.1.1.0.0rc2.dist-info/WHEEL
test_JaqalPaq-0.0.1.1.0.0rc2.dist-info/entry_points.txt
test_JaqalPaq-0.0.1.1.0.0rc2.dist-info/top_level.txt
test_JaqalPaq-0.0.1.1.0.0rc2.dist-info/RECORD
